sigma/pipelines/ocsf/__init__.py
sigma/pipelines/ocsf/ocsf.py
pysigma_pipeline_ocsf-0.1.0.dist-info/LICENSE
pysigma_pipeline_ocsf-0.1.0.dist-info/METADATA
pysigma_pipeline_ocsf-0.1.0.dist-info/WHEEL
pysigma_pipeline_ocsf-0.1.0.dist-info/RECORD
