Metadata-Version: 2.3
Name: pySigma-pipeline-ocsf
Version: 0.1.0
Summary: pySigma OCSF pipeline
License: MIT
Author: Hendrik Baecker
Author-email: hb@process-zero.de
Requires-Python: >=3.9,<4.0
Classifier: License :: OSI Approved :: MIT License
Classifier: Programming Language :: Python :: 3
Classifier: Programming Language :: Python :: 3.9
Classifier: Programming Language :: Python :: 3.10
Classifier: Programming Language :: Python :: 3.11
Classifier: Programming Language :: Python :: 3.12
Classifier: Programming Language :: Python :: 3.13
Requires-Dist: pysigma (>=0.11.0,<0.12.0)
Project-URL: Repository, https://github.com/SigmaHQ/pySigma-pipeline-ocsf
